sun_position_calculator/__init__.py
sun_position_calculator/sun_phase.py
sun_position_calculator/sun_position_calculator.py
sun_position_calculator-1.0.0.dist-info/LICENSE
sun_position_calculator-1.0.0.dist-info/METADATA
sun_position_calculator-1.0.0.dist-info/WHEEL
sun_position_calculator-1.0.0.dist-info/top_level.txt
sun_position_calculator-1.0.0.dist-info/RECORD
