Metadata-Version: 2.1
Name: sun-position-calculator
Version: 1.0.0
Summary: A Python library to calculate the sun's position and phases.
Home-page: https://notabug.org/alimiracle/sun_position_calculator
Author: Ali miracle
Author-email: alimiracle@riseup.net
License: UNKNOWN
Keywords: sun position calculator astronomy phases python library
Platform: UNKNOWN
Classifier: Development Status :: 5 - Production/Stable
Classifier: Intended Audience :: Developers
Classifier: License :: OSI Approved :: GNU General Public License v3 (GPLv3)
Classifier: Operating System :: OS Independent
Classifier: Programming Language :: Python :: 3
License-File: LICENSE
